chromator/__init__.py
chromator/cli.py
chromator/shades.py
chromator-0.6.5.dist-info/WHEEL
chromator-0.6.5.dist-info/entry_points.txt
chromator-0.6.5.dist-info/METADATA
chromator-0.6.5.dist-info/RECORD
