Metadata-Version: 2.4
Name: chromator
Version: 0.6.5
Summary: Color shades generator
Keywords: color shades generator,cli utility
Author: Huib Piguillet
Author-email: Huib Piguillet <huib@proton.me>
License-Expression: MIT
Classifier: Intended Audience :: Developers
Classifier: Topic :: Utilities
Classifier: Topic :: Software Development :: Build Tools
Classifier: Programming Language :: Python :: 3
Classifier: Programming Language :: Python :: 3.12
Classifier: Programming Language :: Python :: 3.13
Classifier: Programming Language :: Python :: 3.14
Classifier: Programming Language :: Python :: 3 :: Only
Requires-Dist: based-utils
Requires-Dist: yachalk
Requires-Python: >=3.14
Project-URL: Github, https://github.com/githuib/chromator
Project-URL: PyPI, https://pypi.org/project/chromator/
